Scrapping/__init__.py
RMVR_WS-0.0.1.dist-info/LICENSE.txt
RMVR_WS-0.0.1.dist-info/METADATA
RMVR_WS-0.0.1.dist-info/WHEEL
RMVR_WS-0.0.1.dist-info/top_level.txt
RMVR_WS-0.0.1.dist-info/RECORD
