Metadata-Version: 2.1
Name: RMVR-WS
Version: 0.0.1
Summary: A simple Scrapping Package
Home-page: https://github.com/pypa/web-scrap
Author: V.Ramachandran
Author-email: rama5864@gmail.com
License: UNKNOWN
Platform: UNKNOWN
Classifier: Programming Language :: Python :: 3
Classifier: License :: OSI Approved :: MIT License
Classifier: Operating System :: OS Independent
Requires-Python: >=3.6
